<annotation>
	<folder>train_images</folder>
	<filename>images121 (2).jpg</filename>
	<path>D:\MyProjects\git\ball_tracker\train_images\images121 (2).jpg</path>
	<source>
		<database>Unknown</database>
	</source>
	<size>
		<width>234</width>
		<height>215</height>
		<depth>3</depth>
	</size>
	<segmented>0</segmented>
	<object>
		<name>ball</name>
		<pose>Unspecified</pose>
		<truncated>0</truncated>
		<difficult>0</difficult>
		<bndbox>
			<xmin>121</xmin>
			<ymin>21</ymin>
			<xmax>187</xmax>
			<ymax>86</ymax>
		</bndbox>
	</object>
</annotation>
